molten/__init__.py
molten/app.py
molten/common.py
molten/components.py
molten/dependency_injection.py
molten/errors.py
molten/helpers.py
molten/middleware.py
molten/parsers.py
molten/py.typed
molten/renderers.py
molten/router.py
molten/settings.py
molten/typing.py
molten/contrib/dramatiq.py
molten/contrib/msgpack.py
molten/contrib/prometheus.py
molten/contrib/request_id.py
molten/contrib/sessions.py
molten/contrib/sqlalchemy.py
molten/contrib/templates.py
molten/contrib/toml_settings.py
molten/contrib/websockets.py
molten/http/__init__.py
molten/http/cookies.py
molten/http/headers.py
molten/http/query_params.py
molten/http/request.py
molten/http/response.py
molten/http/status_codes.py
molten/http/uploaded_file.py
molten/openapi/__init__.py
molten/openapi/documents.py
molten/openapi/handlers.py
molten/openapi/templates/__init__.py
molten/openapi/templates/index.html
molten/testing/__init__.py
molten/testing/client.py
molten/testing/common.py
molten/validation/__init__.py
molten/validation/common.py
molten/validation/field.py
molten/validation/forward.py
molten/validation/schema.py
molten-1.0.2.dist-info/COPYING
molten-1.0.2.dist-info/COPYING.LESSER
molten-1.0.2.dist-info/METADATA
molten-1.0.2.dist-info/WHEEL
molten-1.0.2.dist-info/top_level.txt
molten-1.0.2.dist-info/RECORD
