Metadata-Version: 2.1
Name: molten
Version: 1.0.2
Summary: A minimal, extensible, fast and productive API framework.
Home-page: UNKNOWN
Author: Bogdan Popa
Author-email: bogdan@cleartype.io
License: UNKNOWN
Platform: UNKNOWN
Classifier: Environment :: Web Environment
Classifier: Intended Audience :: Developers
Classifier: License :: OSI Approved :: GNU Lesser General Public License v3 or later (LGPLv3+)
Classifier: Operating System :: OS Independent
Classifier: Programming Language :: Python :: 3 :: Only
Classifier: Programming Language :: Python :: 3.6
Classifier: Programming Language :: Python :: 3.7
Classifier: Programming Language :: Python
Classifier: Topic :: Internet :: WWW/HTTP :: Dynamic Content
Classifier: Topic :: Internet :: WWW/HTTP :: WSGI :: Application
Classifier: Topic :: Software Development :: Libraries :: Application Frameworks
Classifier: Topic :: Software Development :: Libraries :: Python Modules
Requires-Python: >=3.6
Requires-Dist: typing-extensions (<4.0,>=3.6)
Requires-Dist: typing-inspect (<0.7,>=0.3.1)
Provides-Extra: all
Requires-Dist: typing-extensions (<4.0,>=3.6) ; extra == 'all'
Requires-Dist: typing-inspect (<0.7,>=0.3.1) ; extra == 'all'
Provides-Extra: dev
Requires-Dist: typing-extensions (<4.0,>=3.6) ; extra == 'dev'
Requires-Dist: typing-inspect (<0.7,>=0.3.1) ; extra == 'dev'
Requires-Dist: alabaster (>0.7) ; extra == 'dev'
Requires-Dist: sphinx (<1.8) ; extra == 'dev'
Requires-Dist: sphinxcontrib-napoleon ; extra == 'dev'
Requires-Dist: flake8 ; extra == 'dev'
Requires-Dist: flake8-bugbear ; extra == 'dev'
Requires-Dist: flake8-quotes ; extra == 'dev'
Requires-Dist: isort ; extra == 'dev'
Requires-Dist: mypy ; extra == 'dev'
Requires-Dist: bumpversion (<0.6,>0.5) ; extra == 'dev'
Requires-Dist: dramatiq[rabbitmq] (<2.0,>1.3) ; extra == 'dev'
Requires-Dist: gevent ; extra == 'dev'
Requires-Dist: gunicorn (>19.8) ; extra == 'dev'
Requires-Dist: jinja2 (<3.0,>=2.10) ; extra == 'dev'
Requires-Dist: msgpack (<0.6,>0.5) ; extra == 'dev'
Requires-Dist: prometheus-client (<0.3,>=0.2) ; extra == 'dev'
Requires-Dist: sqlalchemy (<2.0,>1.2) ; extra == 'dev'
Requires-Dist: toml (<0.10,>0.9) ; extra == 'dev'
Requires-Dist: wsgicors (<0.8,>=0.7) ; extra == 'dev'
Requires-Dist: pytest ; extra == 'dev'
